py3o.fusion-0.8.9-py2.7-nspkg.pth
py3o.fusion-0.8.9.dist-info/DESCRIPTION.rst
py3o.fusion-0.8.9.dist-info/top_level.txt
py3o.fusion-0.8.9.dist-info/zip-safe
py3o.fusion-0.8.9.dist-info/METADATA
py3o.fusion-0.8.9.dist-info/RECORD
py3o.fusion-0.8.9.dist-info/WHEEL
py3o.fusion-0.8.9.dist-info/metadata.json
py3o.fusion-0.8.9.dist-info/namespace_packages.txt
py3o.fusion-0.8.9.dist-info/entry_points.txt
py3o/fusion/server.py
py3o/fusion/formpage.py
py3o/fusion/template.py
py3o/fusion/indexpage.py
py3o/fusion/log.py
py3o/fusion/autodestroy.py
py3o/fusion/__init__.py
py3o/fusion/featurespage.py
py3o/fusion/templates/scripts.xml
py3o/fusion/templates/features.xml
py3o/fusion/templates/form.xml
py3o/fusion/templates/header.xml
py3o/fusion/templates/index.xml
py3o/fusion/static/css/pygments.css
py3o/fusion/static/css/cover.css
py3o/fusion/static/jquery/1.11.1/jquery.min.js
py3o/fusion/static/examples/odt2pdf.py
py3o/fusion/static/examples/fusion2pdf.py
py3o/fusion/static/examples/complexfusion2pdf.py
py3o/fusion/static/examples/templates/simple.pdf
py3o/fusion/static/examples/templates/fusion2pdf_template.pdf
py3o/fusion/static/examples/templates/fusion2pdf_template.png
py3o/fusion/static/examples/templates/fusion2pdf.odt
py3o/fusion/static/examples/templates/py3o_example_template.odt
py3o/fusion/static/examples/templates/simple.odt
py3o/fusion/static/examples/templates/fusion2pdf.pdf
py3o/fusion/static/examples/.ropeproject/globalnames
py3o/fusion/static/examples/.ropeproject/config.py
py3o/fusion/static/examples/.ropeproject/objectdb
py3o/fusion/static/examples/.ropeproject/history
py3o/fusion/static/examples/images/new_logo.xcf
py3o/fusion/static/examples/images/new_logo.png
py3o/fusion/static/zeroclipboard/ZeroClipboard.min.map
py3o/fusion/static/zeroclipboard/ZeroClipboard.Core.min.map
py3o/fusion/static/zeroclipboard/ZeroClipboard.Core.min.js
py3o/fusion/static/zeroclipboard/ZeroClipboard.swf
py3o/fusion/static/zeroclipboard/ZeroClipboard.min.js
py3o/fusion/static/bootstrap/css/bootstrap-theme.css
py3o/fusion/static/bootstrap/css/bootstrap-theme.min.css
py3o/fusion/static/bootstrap/css/bootstrap.min.css
py3o/fusion/static/bootstrap/css/bootstrap.css.map
py3o/fusion/static/bootstrap/css/bootstrap-theme.css.map
py3o/fusion/static/bootstrap/css/bootstrap.css
