Metadata-Version: 2.0
Name: py3o.fusion
Version: 0.8.9
Summary: A Fusion server that will transform your py3o.template into final LibreOffice documents
Home-page: http://bitbucket.org/faide/py3o.fusion
Author: Florent Aide
Author-email: florent.aide@gmail.com
License: BSD License
Keywords: LibreOffice OpenOffice templating PDF Fusion
Platform: UNKNOWN
Classifier: Programming Language :: Python
Classifier: Topic :: Internet :: WWW/HTTP :: HTTP Servers
Classifier: Topic :: Text Processing :: General
Classifier: Development Status :: 4 - Beta
Classifier: Intended Audience :: Developers
Classifier: License :: OSI Approved :: BSD License
Classifier: Operating System :: OS Independent
Requires-Dist: setuptools
Requires-Dist: py3o.template (>=0.9.13)
Requires-Dist: py3o.renderclient (>=0.2)
Requires-Dist: py3o.formats (>=0.3)
Requires-Dist: py3o.types (>=0.1.1)
Requires-Dist: twisted
Requires-Dist: pygments
